itaxotools/__pyinstaller/hook-itaxotools.spart_parser.gui.py
itaxotools/spart_parser/__init__.py
itaxotools/spart_parser/main.py
itaxotools/spart_parser/gui/__init__.py
itaxotools/spart_parser/gui/main.py
itaxotools/spart_parser/gui/model.py
itaxotools/spart_parser/gui/utility.py
itaxotools/spart_parser/gui/app/__init__.py
itaxotools/spart_parser/gui/app/resources.py
itaxotools/spart_parser/gui/app/skin.py
itaxotools/spart_parser/gui/logos/spart.ico
itaxotools/spart_parser/gui/logos/spart.svg
itaxotools_spart_parser-0.1.3.dist-info/LICENSE
itaxotools_spart_parser-0.1.3.dist-info/METADATA
itaxotools_spart_parser-0.1.3.dist-info/WHEEL
itaxotools_spart_parser-0.1.3.dist-info/entry_points.txt
itaxotools_spart_parser-0.1.3.dist-info/top_level.txt
itaxotools_spart_parser-0.1.3.dist-info/RECORD
