Metadata-Version: 2.1
Name: itaxotools-spart-parser
Version: 0.1.3
Summary: Parse and write SPART files
Author: Khushil Prajapati
Author-email: Stefanos Patmanidis <stefanpatman91@gmail.com>
Project-URL: Homepage, https://itaxotools.org/
Project-URL: Source, https://github.com/iTaxoTools/SpartParser
Classifier: License :: OSI Approved :: GNU General Public License v3 or later (GPLv3+)
Classifier: Development Status :: 5 - Production/Stable
Classifier: Programming Language :: Python
Classifier: Programming Language :: Python :: 3.10
Classifier: Programming Language :: Python :: 3.11
Classifier: Programming Language :: Python :: 3.12
Classifier: Programming Language :: Python :: Implementation :: CPython
Requires-Python: <4,>=3.10.2
License-File: LICENSE
Provides-Extra: dev
Requires-Dist: setuptools-scm ; extra == 'dev'
Requires-Dist: pre-commit ; extra == 'dev'
Requires-Dist: ruff ; extra == 'dev'
Requires-Dist: pytest ; extra == 'dev'
Requires-Dist: pytest-qt ; extra == 'dev'
Requires-Dist: pytest-xvfb ; extra == 'dev'
Requires-Dist: pyinstaller ; extra == 'dev'
Requires-Dist: memory-profiler ; extra == 'dev'
Requires-Dist: matplotlib ; extra == 'dev'
Provides-Extra: gui
Requires-Dist: itaxotools-common ; extra == 'gui'
Requires-Dist: pyside6 ; extra == 'gui'
